README.md
pyklopp/__init__.py
pyklopp/__main__.py
pyklopp/__version__.py
pyklopp/console/__init__.py
pyklopp/console/application.py
pyklopp/console/commands/__init__.py
pyklopp/console/commands/eval.py
pyklopp/console/commands/init.py
pyklopp/console/commands/train.py
pyklopp/defaults.py
pyklopp/initializer.py
pyklopp/loading.py
pyklopp/metadata.py
pyklopp/schema/metadata-0.1.0.json
pyklopp/util.py
pyproject.toml
pyklopp-0.3.2.dist-info/entry_points.txt
pyklopp-0.3.2.dist-info/WHEEL
pyklopp-0.3.2.dist-info/METADATA
pyklopp-0.3.2.dist-info/RECORD
