Metadata-Version: 2.1
Name: pyklopp
Version: 0.3.2
Summary: 
Home-page: https://github.com/innvariant/pyklopp
License: MIT
Keywords: machine learning,inference,training
Author: Julian Stier
Author-email: julian.stier@uni-passau.de
Requires-Python: >=3.6.1,<4.0.0
Classifier: License :: OSI Approved :: MIT License
Classifier: Programming Language :: Python :: 3
Classifier: Programming Language :: Python :: 3.7
Classifier: Programming Language :: Python :: 3.8
Requires-Dist: cleo (>=0.7,<0.8)
Requires-Dist: importlib-metadata (>=1.5.0,<2.0.0)
Requires-Dist: importlib-resources (>=1.4.0,<2.0.0)
Requires-Dist: jsonschema (>=3.2.0,<4.0.0)
Requires-Dist: pytorch-ignite (>=0.2,<0.3)
Requires-Dist: semantic_version (>=2.8.4,<3.0.0)
Requires-Dist: torch (>=1.3)
Requires-Dist: torchvision (>=0.4)
Requires-Dist: tqdm (>=4.40,<5.0)
Project-URL: Documentation, https://github.com/innvariant/pyklopp
Project-URL: Repository, https://github.com/innvariant/pyklopp
